Workbook

Sheet Summary
A1: id | B1: scenario | C1: rate_dst | D1: rate_ad | E1: rate_ftt | F1: rate_wealth | G1: rate_aviation | H1: rate_luxury | I1: rmsd_from_eu_mean | J1: max_cost | K1: max_cost_country | L1: range_cost | M1: homogeneity_minimax | N1: homogeneity_sq_dev | O1: coef_dst | P1: coef_ad | Q1: coef_ftt | R1: coef_wealth | S1: coef_aviation | T1: coef_luxury | U1: share_dst | V1: share_ad | W1: share_ftt | X1: share_wealth | Y1: share_aviation | Z1: share_luxury | AA1: total_pct_gni | AB1: total_eur_bn | AC1: new_funds_eur_bn | AD1: min_cost | AE1: min_cost_country | AF1: max_frugal_cost | AG1: max_frugal_cost_country | AH1: min_state_gain | AI1: min_state_gain_country
A2: R0 | B2: Report rates (EUR 102.6 bn) | C2: 3 | D2: 15 | E2: 0.5 | F2: 0.5 | G2: 20 | H2: 20 | I2: 0.16406235 | J2: 1.6284698 | K2: Cyprus | L2: 1.293196 | M2: 0.43272633 | N2: 0.81114997 | O2: 1 | P2: 1 | Q2: 1 | R2: 1 | S2: 1 | T2: 1 | U2: 5.731061 | V2: 9.3763277 | W2: 8.1233891 | X2: 25.598739 | Y2: 10.23433 | Z2: 40.936153 | AA2: 0.70468176 | AB2: 102.5988 | AC2: 29.758401 | AD2: 0.33527375 | AE2: Slovakia | AF2: 0.75100649 | AG2: Austria | AH2: 0.24162953 | AI2: France
A3: A1 | B3: Min max cost | C3: 7.7272946 | D3: 60 | E3: 0.63469574 | F3: 0.66236725 | G3: 6.8583469 | H3: 0 | I3: 0.1589893 | J3: 0.88390302 | K3: Luxembourg | L3: 0.56806224 | M3: 0.79723877 | N3: 0.81591452 | O3: 2.5757649 | P3: 4 | Q3: 1.2693915 | R3: 1.3247345 | S3: 0.34291734 | T3: 0 | U3: 14.761866 | V3: 37.505311 | W3: 10.311761 | X3: 33.911533 | Y3: 3.5095293 | Z3: 0 | AA3: 0.70468176 | AB3: 102.5988 | AC3: 20.875696 | AD3: 0.31584078 | AE3: Romania | AF3: 0.87473796 | AG3: Netherlands | AH3: 0.30263882 | AI3: France
A4: A2 | B4: Min squared deviation | C4: 9.6152012 | D4: 46.464053 | E4: 0.20929601 | F4: 0.36979969 | G4: 0 | H4: 14.781175 | I4: 0.11428179 | J4: 1.3368173 | K4: Cyprus | L4: 0.896529 | M4: 0.52713391 | N4: 0.86045558 | O4: 3.2050671 | P4: 3.0976035 | Q4: 0.41859202 | R4: 0.73959938 | S4: 0 | T4: 0.73905875 | U4: 18.368435 | V4: 29.044146 | W4: 3.4003859 | X4: 18.932812 | Y4: 0 | Z4: 30.254222 | AA4: 0.70468176 | AB4: 102.5988 | AC4: 22.001726 | AD4: 0.44028834 | AE4: Romania | AF4: 0.78422491 | AG4: Austria | AH4: 0.29490488 | AI4: France
A5: B1 | B5: Min max cost, frugal <= EU mean | C5: 12 | D5: 0 | E5: 0.49125267 | F5: 0.98627521 | G5: 36.347624 | H5: 0 | I5: 0.1536344 | J5: 1.2664983 | K5: Cyprus | L5: 0.8937446 | M5: 0.55640168 | N5: 0.82100488 | O5: 4 | P5: 0 | Q5: 0.98250534 | R5: 1.9725504 | S5: 1.8173812 | T5: 0 | U5: 22.924244 | V5: 0 | W5: 7.9812732 | X5: 50.494804 | Y5: 18.599679 | Z5: 0 | AA5: 0.70468176 | AB5: 102.5988 | AC5: 31.084238 | AD5: 0.37275365 | AE5: Slovakia | AF5: 0.70468176 | AG5: Austria | AH5: 0.23252325 | AI5: France
A6: B2 | B6: Min squared deviation, frugal <= EU mean | C6: 12 | D6: 0 | E6: 0.48997828 | F6: 0.82782654 | G6: 33.038063 | H6: 4.8008587 | I6: 0.15147529 | J6: 1.3792027 | K6: Cyprus | L6: 0.96958543 | M6: 0.51093414 | N6: 0.82307534 | O6: 4 | P6: 0 | Q6: 0.97995656 | R6: 1.6556531 | S6: 1.6519031 | T6: 0.24004293 | U6: 22.924244 | V6: 0 | W6: 7.9605685 | X6: 42.382631 | Y6: 16.906122 | Z6: 9.8264343 | AA6: 0.70468176 | AB6: 102.5988 | AC6: 29.451045 | AD6: 0.4096173 | AE6: Slovakia | AF6: 0.70468176 | AG6: Austria | AH6: 0.24374055 | AI6: France
A7: C1 | B7: Max min State budget gain, then min max cost | C7: 12 | D7: 60 | E7: 1.430709 | F7: 0 | G7: 31.904404 | H7: 0 | I7: 0.18452926 | J7: 1.228953 | K7: Malta | L7: 0.83977961 | M7: 0.57339996 | N7: 0.79247975 | O7: 4 | P7: 4 | Q7: 2.8614179 | R7: 0 | S7: 1.5952202 | T7: 0 | U7: 22.92425 | V7: 37.50532 | W7: 23.244417 | X7: 0 | Y7: 16.326014 | Z7: 0 | AA7: 0.70468159 | AB7: 102.59878 | AC7: 0 | AD7: 0.38917337 | AE7: Slovenia | AF7: 1.2289529 | AG7: Netherlands | AH7: 0.44601968 | AI7: France
A8: C2 | B8: Max min State budget gain, then min squared deviation | C8: 12 | D8: 60 | E8: 1.1829056 | F8: 0 | G8: 39.772018 | H8: 0 | I8: 0.17955852 | J8: 1.4097107 | K8: Malta | L8: 1.0155724 | M8: 0.49987664 | N8: 0.79693463 | O8: 4 | P8: 4 | Q8: 2.3658111 | R8: 0 | S8: 1.9886009 | T8: 0 | U8: 22.924254 | V8: 37.505327 | W8: 19.218413 | X8: 0 | Y8: 20.352007 | Z8: 0 | AA8: 0.70468146 | AB8: 102.59876 | AC8: 0 | AD8: 0.39413831 | AE8: Slovenia | AF8: 1.1345694 | AG8: Netherlands | AH8: 0.44601955 | AI8: France
A9: Custom | B9: Custom rates: edit the rate cells, indicators are computed by Excel | C9: 3 | D9: 15 | E9: 0.5 | F9: 0.5 | G9: 20 | H9: 20 | I9: =SQRT(SUMPRODUCT(Data!$J$3:$J$29,(Data!$I$3:$I$29-AA9)^2)/SUM(Data!$J$3:$J$29)) | J9: =MAX(Data!$I$3:$I$29) | K9: =INDEX(Data!$A$3:$A$29,MATCH(MAX(Data!$I$3:$I$29),Data!$I$3:$I$29,0)) | L9: =MAX(Data!$I$3:$I$29)-MIN(Data!$I$3:$I$29) | M9: =AA9/J9 | N9: =AA9/(AA9+I9) | O9: =C9/Data!C$2 | P9: =D9/Data!D$2 | Q9: =E9/Data!E$2 | R9: =F9/Data!F$2 | S9: =G9/Data!G$2 | T9: =H9/Data!H$2 | AA9: =SUMPRODUCT(Data!$I$3:$I$29,Data!$B$3:$B$29)/SUM(Data!$B$3:$B$29) | AB9: =AA9*SUM(Data!$B$3:$B$29)/100 | AD9: =MIN(Data!$I$3:$I$29) | AE9: =INDEX(Data!$A$3:$A$29,MATCH(MIN(Data!$I$3:$I$29),Data!$I$3:$I$29,0))
A10: H_minimax | B10: Homogeneity score of each tax alone: minimax | C10: 0.42960044 | D10: 0.57172975 | E10: 0.2443763 | F10: 0.43770507 | G10: 0.15695264 | H10: 0.30116266
A11: H_sq_dev | B11: Homogeneity score of each tax alone: squared deviations | C11: 0.64238731 | D11: 0.76723685 | E11: 0.51089519 | F11: 0.72972932 | G11: 0.52696283 | H11: 0.73338121

Sheet Summary_lux
A1: id | B1: scenario | C1: rate_dst | D1: rate_ad | E1: rate_ftt | F1: rate_wealth | G1: rate_aviation | H1: rate_lux_automotive | I1: rate_lux_personal | J1: rate_lux_hospitality | K1: rate_lux_wines | L1: rate_lux_gourmet | M1: rate_lux_design | N1: rate_lux_yachts | O1: rmsd_from_eu_mean | P1: max_cost | Q1: max_cost_country | R1: range_cost | S1: homogeneity_minimax | T1: homogeneity_sq_dev | U1: coef_dst | V1: coef_ad | W1: coef_ftt | X1: coef_wealth | Y1: coef_aviation | Z1: coef_lux_automotive | AA1: coef_lux_personal | AB1: coef_lux_hospitality | AC1: coef_lux_wines | AD1: coef_lux_gourmet | AE1: coef_lux_design | AF1: coef_lux_yachts | AG1: share_dst | AH1: share_ad | AI1: share_ftt | AJ1: share_wealth | AK1: share_aviation | AL1: share_lux_automotive | AM1: share_lux_personal | AN1: share_lux_hospitality | AO1: share_lux_wines | AP1: share_lux_gourmet | AQ1: share_lux_design | AR1: share_lux_yachts | AS1: total_pct_gni | AT1: total_eur_bn | AU1: new_funds_eur_bn | AV1: min_cost | AW1: min_cost_country | AX1: max_frugal_cost | AY1: max_frugal_cost_country | AZ1: min_state_gain | BA1: min_state_gain_country
A2: R0 | B2: Report rates (EUR 102.6 bn) | C2: 3 | D2: 15 | E2: 0.5 | F2: 0.5 | G2: 20 | H2: 20 | I2: 20 | J2: 20 | K2: 20 | L2: 20 | M2: 20 | N2: 20 | O2: 0.16406235 | P2: 1.6284698 | Q2: Cyprus | R2: 1.293196 | S2: 0.43272633 | T2: 0.81114997 | U2: 1 | V2: 1 | W2: 1 | X2: 1 | Y2: 1 | Z2: 1 | AA2: 1 | AB2: 1 | AC2: 1 | AD2: 1 | AE2: 1 | AF2: 1 | AG2: 5.731061 | AH2: 9.3763277 | AI2: 8.1233891 | AJ2: 25.598739 | AK2: 10.23433 | AL2: 12.32524 | AM2: 11.023838 | AN2: 7.3560114 | AO2: 3.0412156 | AP2: 2.462026 | AQ2: 1.5065254 | AR2: 3.2212963 | AS2: 0.70468176 | AT2: 102.5988 | AU2: 29.758401 | AV2: 0.33527375 | AW2: Slovakia | AX2: 0.75100649 | AY2: Austria | AZ2: 0.24162953 | BA2: France
A3: A1 | B3: Min max cost | C3: 6.2709525 | D3: 60 | E3: 0.5634314 | F3: 0.49078716 | G3: 3.0723163 | H3: 5.3507829 | I3: 0 | J3: 0 | K3: 0 | L3: 0 | M3: 80 | N3: 33.143187 | O3: 0.13353585 | P3: 0.85231615 | Q3: Luxembourg | R3: 0.54188086 | S3: 0.82678447 | T3: 0.84069071 | U3: 2.0903175 | V3: 4 | W3: 1.1268628 | X3: 0.98157431 | Y3: 0.15361581 | Z3: 0.26753915 | AA3: 0 | AB3: 0 | AC3: 0 | AD3: 0 | AE3: 4 | AF3: 1.6571593 | AG3: 11.979737 | AH3: 37.505311 | AI3: 9.1539451 | AJ3: 25.127065 | AK3: 1.5721549 | AL3: 3.2974843 | AM3: 0 | AN3: 0 | AO3: 0 | AP3: 0 | AQ3: 6.0261015 | AR3: 5.3382012 | AS3: 0.70468176 | AT3: 102.5988 | AU3: 20.482313 | AV3: 0.31043529 | AW3: Romania | AX3: 0.85231615 | AY3: Netherlands | AZ3: 0.3053407 | BA3: France
A4: A2 | B4: Min squared deviation | C4: 10.578084 | D4: 7.6717775 | E4: 0.55279089 | F4: 0.011439939 | G4: 12.134597 | H4: 72.215833 | I4: 10.005873 | J4: 0 | K4: 7.330845 | L4: 0 | M4: 80 | N4: 12.792811 | O4: 0.074891963 | P4: 1.2479881 | Q4: Luxembourg | R4: 0.79682025 | S4: 0.56465421 | T4: 0.90393216 | U4: 3.5260279 | V4: 0.51145183 | W4: 1.1055818 | X4: 0.022879878 | Y4: 0.60672983 | Z4: 3.6107916 | AA4: 0.50029367 | AB4: 0 | AC4: 0.36654225 | AD4: 0 | AE4: 4 | AF4: 0.63964053 | AG4: 20.207881 | AH4: 4.79554 | AI4: 8.9810711 | AJ4: 0.58569604 | AK4: 6.2094733 | AL4: 44.503875 | AM4: 5.5151562 | AN4: 0 | AO4: 1.114734 | AP4: 0 | AQ4: 6.0261015 | AR4: 2.0604716 | AS4: 0.70468176 | AT4: 102.5988 | AU4: 20.61367 | AV4: 0.45116789 | AW4: Finland | AX4: 0.76847194 | AY4: Netherlands | AZ4: 0.3044385 | BA4: France
A5: B1 | B5: Min max cost, frugal <= EU mean | C5: 12 | D5: 15.228886 | E5: 0.42521526 | F5: 0.84139025 | G5: 0 | H5: 0 | I5: 0 | J5: 0 | K5: 0 | L5: 45.734256 | M5: 80 | N5: 36.723531 | O5: 0.12835476 | P5: 0.96132171 | Q5: Luxembourg | R5: 0.55768796 | S5: 0.73303427 | T5: 0.84591941 | U5: 4 | V5: 1.0152591 | W5: 0.85043052 | X5: 1.6827805 | Y5: 0 | Z5: 0 | AA5: 0 | AB5: 0 | AC5: 0 | AD5: 2.2867128 | AE5: 4 | AF5: 1.8361765 | AG5: 22.924244 | AH5: 9.5194018 | AI5: 6.908378 | AJ5: 43.077059 | AK5: 0 | AL5: 0 | AM5: 0 | AN5: 0 | AO5: 0 | AP5: 5.6299465 | AQ5: 6.0261015 | AR5: 5.9148687 | AS5: 0.70468176 | AT5: 102.5988 | AU5: 32.527112 | AV5: 0.40363375 | AW5: Finland | AX5: 0.70468176 | AY5: Austria | AZ5: 0.22261313 | BA5: France
A6: B2 | B6: Min squared deviation, frugal <= EU mean | C6: 11.995459 | D6: 0 | E6: 0.42350448 | F6: 0.10960011 | G6: 9.029478 | H6: 71.033336 | I6: 13.136579 | J6: 0 | K6: 0 | L6: 0 | M6: 71.470323 | N6: 22.180813 | O6: 0.078026814 | P6: 1.2772854 | Q6: Luxembourg | R6: 0.84089476 | S6: 0.55170267 | T6: 0.90031179 | U6: 3.9984865 | V6: 0 | W6: 0.84700896 | X6: 0.21920022 | Y6: 0.4514739 | Z6: 3.5516668 | AA6: 0.65682897 | AB6: 0 | AC6: 0 | AD6: 0 | AE6: 3.5735162 | AF6: 1.1090406 | AG6: 22.91557 | AH6: 0 | AI6: 6.8805834 | AJ6: 5.6112493 | AK6: 4.6205328 | AL6: 43.775147 | AM6: 7.2407759 | AN6: 0 | AO6: 0 | AP6: 0 | AQ6: 5.3835928 | AR6: 3.5725485 | AS6: 0.70468176 | AT6: 102.5988 | AU6: 23.964451 | AV6: 0.43639062 | AW6: Finland | AX6: 0.70468176 | AY6: Netherlands | AZ6: 0.28142425 | BA6: France
A7: C1 | B7: Max min State budget gain, then min max cost | C7: 12 | D7: 60 | E7: 1.4307082 | F7: 0 | G7: 31.90439 | H7: 0 | I7: 0 | J7: 0 | K7: 0 | L7: 0 | M7: 0 | N7: 0 | O7: 0.1845292 | P7: 1.2289527 | Q7: Malta | R7: 0.83977931 | S7: 0.5734 | T7: 0.79247977 | U7: 4 | V7: 4 | W7: 2.8614165 | X7: 0 | Y7: 1.5952195 | Z7: 0 | AA7: 0 | AB7: 0 | AC7: 0 | AD7: 0 | AE7: 0 | AF7: 0 | AG7: 22.924254 | AH7: 37.505327 | AI7: 23.244409 | AJ7: 0 | AK7: 16.32601 | AL7: 0 | AM7: 0 | AN7: 0 | AO7: 0 | AP7: 0 | AQ7: 0 | AR7: 0 | AS7: 0.70468146 | AT7: 102.59876 | AU7: 0 | AV7: 0.38917336 | AW7: Slovenia | AX7: 1.2289526 | AY7: Netherlands | AZ7: 0.44601955 | BA7: France
A8: C2 | B8: Max min State budget gain, then min squared deviation | C8: 12 | D8: 60 | E8: 1.1829053 | F8: 0 | G8: 39.772026 | H8: 0 | I8: 0 | J8: 0 | K8: 0 | L8: 0 | M8: 0 | N8: 0 | O8: 0.17955852 | P8: 1.4097109 | Q8: Malta | R8: 1.0155726 | S8: 0.49987657 | T8: 0.79693463 | U8: 4 | V8: 4 | W8: 2.3658106 | X8: 0 | Y8: 1.9886013 | Z8: 0 | AA8: 0 | AB8: 0 | AC8: 0 | AD8: 0 | AE8: 0 | AF8: 0 | AG8: 22.924254 | AH8: 37.505327 | AI8: 19.218409 | AJ8: 0 | AK8: 20.352011 | AL8: 0 | AM8: 0 | AN8: 0 | AO8: 0 | AP8: 0 | AQ8: 0 | AR8: 0 | AS8: 0.70468146 | AT8: 102.59876 | AU8: 0 | AV8: 0.39413831 | AW8: Slovenia | AX8: 1.1345693 | AY8: Netherlands | AZ8: 0.44601955 | BA8: France
A9: Custom | B9: Custom rates: edit the rate cells, indicators are computed by Excel | C9: 3 | D9: 15 | E9: 0.5 | F9: 0.5 | G9: 20 | H9: 20 | I9: 20 | J9: 20 | K9: 20 | L9: 20 | M9: 20 | N9: 20 | O9: =SQRT(SUMPRODUCT(Data_lux!$P$3:$P$29,(Data_lux!$O$3:$O$29-AS9)^2)/SUM(Data_lux!$P$3:$P$29)) | P9: =MAX(Data_lux!$O$3:$O$29) | Q9: =INDEX(Data_lux!$A$3:$A$29,MATCH(MAX(Data_lux!$O$3:$O$29),Data_lux!$O$3:$O$29,0)) | R9: =MAX(Data_lux!$O$3:$O$29)-MIN(Data_lux!$O$3:$O$29) | S9: =AS9/P9 | T9: =AS9/(AS9+O9) | U9: =C9/Data_lux!C$2 | V9: =D9/Data_lux!D$2 | W9: =E9/Data_lux!E$2 | X9: =F9/Data_lux!F$2 | Y9: =G9/Data_lux!G$2 | Z9: =H9/Data_lux!H$2 | AA9: =I9/Data_lux!I$2 | AB9: =J9/Data_lux!J$2 | ... AF9: =N9/Data_lux!N$2 | AS9: =SUMPRODUCT(Data_lux!$O$3:$O$29,Data_lux!$B$3:$B$29)/SUM(Data_lux!$B$3:$B$29) | AT9: =AS9*SUM(Data_lux!$B$3:$B$29)/100 | AV9: =MIN(Data_lux!$O$3:$O$29) | AW9: =INDEX(Data_lux!$A$3:$A$29,MATCH(MIN(Data_lux!$O$3:$O$29),Data_lux!$O$3:$O$29,0))
A10: H_minimax | B10: Homogeneity score of each tax alone: minimax | C10: 0.42960044 | D10: 0.57172975 | E10: 0.2443763 | F10: 0.43770507 | G10: 0.15695264 | H10: 0.32878728 | I10: 0.28100347 | J10: 0.11075279 | K10: 0.23513284 | L10: 0.3518285 | M10: 0.41727049 | N10: 0.095349512
A11: H_sq_dev | B11: Homogeneity score of each tax alone: squared deviations | C11: 0.64238731 | D11: 0.76723685 | E11: 0.51089519 | F11: 0.72972932 | G11: 0.52696283 | H11: 0.76962505 | I11: 0.67594471 | J11: 0.49475431 | K11: 0.72414291 | L11: 0.67497151 | M11: 0.64322624 | N11: 0.40660894

Sheet Parameters
A1: parameter | B1: value | C1: unit | D1: description
A2: Total new revenues (target) | B2: 102.5988 | C2: EUR bn | D2: Input: edit, then rerun Rscript min_heterogeneity.R (empty = report's total)
A3: Total new revenues (target) | B3: =B2/B5*100 | C3: % of EU GNI | D3: = B2 / B5 x 100
A4: Report's total at the report's rates | B4: 102.5988 | C4: EUR bn | D4: 0.705% of EU GNI
A5: EU27 GNI | B5: 14559.594 | C5: EUR bn | D5: Sum of Member States' GNI (combined.xlsx)

Sheet Notes
A1: id | B1: scenario
A2: R0 | B2: Report rates (EUR 102.6 bn)
A3: A1 | B3: Min max cost
A4: A2 | B4: Min squared deviation
A5: B1 | B5: Min max cost, frugal <= EU mean
A6: B2 | B6: Min squared deviation, frugal <= EU mean
A7: C1 | B7: Max min State budget gain, then min max cost
A8: C2 | B8: Max min State budget gain, then min squared deviation
B10: note
B11: Source: combined.xlsx (Table 2 = tables/table_gni.tex, Table 4 = tables/table_scenario_gni.tex) and disaggregated_luxury_base.csv. Script: min_heterogeneity.R.
B12: To change the revenue target, edit Parameters!B2 (EUR bn) and rerun Rscript min_heterogeneity.R: Excel does not recompute the optimisations. An empty cell resets it to the report's total.
B13: Summary: the report's 6 taxes. Summary_lux: same, with the luxury tax split into 7 category-specific taxes (report's rate 20% each). Each country's luxury revenue (Table 2) is split across categories in proportion to its category bases in disaggregated_luxury_base.csv, so country totals at 20% are unchanged; 1/3 of each category's revenue finances new funds.
B14: Coefficients c_j >= 0 multiply the report's rates. Revenues are assumed proportional to rates (no additional behavioural response).
B15: Constraint: total new revenues = EUR 102.6 bn = 0.705% of EU GNI (EUR 14560 bn). At the report's rates the total is EUR 102.6 bn (0.705%).
B16: Cost of country i = sum over taxes of c_j x (Table 2 cost at the report's rate), in % of national GNI. The EU mean is GNI-weighted and equals the target by construction.
B17: A1/B1/C1: minimise the maximum country cost (linear programme). A2/B2/C2: minimise the sum over the 27 Member States of squared deviations of cost from the EU mean, each weighted by its population (Eurostat, 1 January 2025; exact QP, primal active-set method).
B18: B1-B2: additional constraint cost <= EU mean for Austria, Germany, Ireland, Netherlands, Sweden.
B19: C1-C2: maximise the minimum State budget gain (Table 4, col. 5) = (new revenues financing the EU budget - EUR 14 bn budget expansion) / EU GNI - foregone domestic revenues (fixed) / national GNI; ties broken by min max cost (C1) or min squared deviation (C2). The gain differs across countries only through foregone revenues, so this amounts to maximising the EU-budget share: no wealth or luxury tax.
B20: Row 9 of the summary tabs: custom rates (edit the rate cells); coefficients, total, RMSD, max/min cost, range and homogeneity scores are computed by Excel from the Data tabs (Table 2 costs at the report's rates).
B21: Rows 10-11 of the summary tabs: homogeneity scores of each tax alone (independent of its rate).
... B24: Rates are capped at 4 times the report's rate (0 <= c_j <= 4).

Sheet Cost_pct_GNI
A1: country | B1: R0 | C1: A1 | D1: A2 | E1: B1 | F1: B2 | G1: C1 | H1: C2 | I1: is_frugal
A2: Austria | B2: 0.75100649 | C2: 0.74216 | D2: 0.78422491 | E2: 0.70468176 | F2: 0.70468176 | G2: 0.58172106 | H2: 0.60303827 | I2: TRUE
A3: Belgium | B3: 0.55248984 | C3: 0.46862964 | D3: 0.55049393 | E3: 0.54337363 | F3: 0.55499199 | G3: 0.41902402 | H3: 0.43296773 | I3: FALSE
A4: Bulgaria | B4: 0.73341326 | C4: 0.4675622 | D4: 0.71313964 | E4: 0.66027933 | F4: 0.71918076 | G4: 0.62106958 | H4: 0.66823064 | I4: FALSE
A5: Croatia | B5: 0.88926956 | C5: 0.51474764 | D5: 0.84390597 | E5: 0.7122739 | F5: 0.8002614 | G5: 0.73596724 | H5: 0.79537079 | I5: FALSE
A6: Cyprus | B6: 1.6284698 | C6: 0.88390302 | D6: 1.3368173 | E6: 1.2664983 | F6: 1.3792027 | G6: 1.101571 | H6: 1.2208208 | I6: FALSE
A7: Czechia | B7: 0.6773244 | C7: 0.88390302 | D7: 0.93224104 | E7: 0.6981368 | F7: 0.71034093 | G7: 0.85188226 | H7: 0.86880207 | I7: FALSE
A8: Denmark | B8: 0.53571346 | C8: 0.64620006 | D8: 0.58072412 | E8: 0.59545852 | F8: 0.5750034 | G8: 0.63446139 | H8: 0.64804604 | I8: FALSE
A9: Estonia | B9: 0.53176878 | C9: 0.61163242 | D9: 0.68657964 | E9: 0.60671319 | F9: 0.62026751 | G9: 0.67894341 | H9: 0.70551925 | I9: FALSE
A10: Finland | B10: 0.4066163 | C10: 0.44792121 | D10: 0.45820364 | E10: 0.42012714 | F10: 0.42857403 | G10: 0.55622513 | H10: 0.56632549 | I10: FALSE
A11: France | B11: 0.87414565 | C11: 0.88390302 | D11: 0.83029361 | E11: 0.88632866 | F11: 0.87702654 | G11: 0.85342457 | H11: 0.81293249 | I11: FALSE
A12: Germany | B12: 0.6201607 | C12: 0.72076496 | D12: 0.65223581 | E12: 0.65691474 | F12: 0.63180209 | G12: 0.57714993 | H12: 0.5708174 | I12: TRUE
A13: Greece | B13: 0.97469475 | C13: 0.46371368 | D13: 0.66868148 | E13: 0.93774131 | F13: 0.98021512 | G13: 0.87926042 | H13: 1.0019378 | I13: FALSE
... A28: Sweden | B28: 0.54564435 | C28: 0.76724596 | D28: 0.69416735 | E28: 0.5241898 | F28: 0.51844966 | G28: 0.77748043 | H28: 0.77476735 | I28: TRUE
A29: European Union (GNI-weighted) | B29: 0.70468176 | C29: 0.70468176 | D29: 0.70468176 | E29: 0.70468176 | F29: 0.70468176 | G29: 0.70468159 | H29: 0.70468146

Sheet State_budget_gain_pct_GNI
A1: country | B1: R0 | C1: A1 | D1: A2 | E1: B1 | F1: B2 | G1: C1 | H1: C2
A2: Austria | B2: 0.37932441 | C2: 0.4403337 | D2: 0.43259976 | E2: 0.37021813 | F2: 0.38143543 | G2: 0.58371456 | H2: 0.58371443
A3: Belgium | B3: 0.39208267 | C3: 0.45309196 | D3: 0.44535803 | E3: 0.38297639 | F3: 0.3941937 | G3: 0.59647283 | H3: 0.5964727
A4: Bulgaria | B4: 0.40413491 | C4: 0.4651442 | D4: 0.45741026 | E4: 0.39502863 | F4: 0.40624593 | G4: 0.60852506 | H4: 0.60852493
A5: Croatia | B5: 0.40413491 | C5: 0.4651442 | D5: 0.45741026 | E5: 0.39502863 | F5: 0.40624593 | G5: 0.60852506 | H5: 0.60852493
A6: Cyprus | B6: 0.40413491 | C6: 0.4651442 | D6: 0.45741026 | E6: 0.39502863 | F6: 0.40624593 | G6: 0.60852506 | H6: 0.60852493
A7: Czechia | B7: 0.40413491 | C7: 0.4651442 | D7: 0.45741026 | E7: 0.39502863 | F7: 0.40624593 | G7: 0.60852506 | H7: 0.60852493
A8: Denmark | B8: 0.40413491 | C8: 0.4651442 | D8: 0.45741026 | E8: 0.39502863 | F8: 0.40624593 | G8: 0.60852506 | H8: 0.60852493
A9: Estonia | B9: 0.40413491 | C9: 0.4651442 | D9: 0.45741026 | E9: 0.39502863 | F9: 0.40624593 | G9: 0.60852506 | H9: 0.60852493
A10: Finland | B10: 0.40413491 | C10: 0.4651442 | D10: 0.45741026 | E10: 0.39502863 | F10: 0.40624593 | G10: 0.60852506 | H10: 0.60852493
A11: France | B11: 0.24162953 | C11: 0.30263882 | D11: 0.29490488 | E11: 0.23252325 | F11: 0.24374055 | G11: 0.44601968 | H11: 0.44601955
A12: Germany | B12: 0.40413491 | C12: 0.4651442 | D12: 0.45741026 | E12: 0.39502863 | F12: 0.40624593 | G12: 0.60852506 | H12: 0.60852493
A13: Greece | B13: 0.39158522 | C13: 0.45259451 | D13: 0.44486057 | E13: 0.38247894 | F13: 0.39369624 | G13: 0.59597537 | H13: 0.59597524
... A29: European Union (GNI-weighted) | B29: 0.35915068 | C29: 0.42015997 | D29: 0.41242604 | E29: 0.3500444 | F29: 0.36126171 | G29: 0.56354084 | H29: 0.5635407

Sheet Cost_by_tax
A1: id | B1: country | C1: tax | D1: rate | E1: cost_pct_gni
A2: R0 | B2: Austria | C2: DST | D2: 3 | E2: 0.035051253
A3: R0 | B3: Belgium | C3: DST | D3: 3 | E3: 0.039648098
A4: R0 | B4: Bulgaria | C4: DST | D4: 3 | E4: 0.072600829
A5: R0 | B5: Croatia | C5: DST | D5: 3 | E5: 0.078675515
A6: R0 | B6: Cyprus | C6: DST | D6: 3 | E6: 0.072760346
A7: R0 | B7: Czechia | C7: DST | D7: 3 | E7: 0.07821666
A8: R0 | B8: Denmark | C8: DST | D8: 3 | E8: 0.031001877
A9: R0 | B9: Estonia | C9: DST | D9: 3 | E9: 0.074436066
A10: R0 | B10: Finland | C10: DST | D10: 3 | E10: 0.037978599
A11: R0 | B11: France | C11: DST | D11: 3 | E11: 0.042102254
A12: R0 | B12: Germany | C12: DST | D12: 3 | E12: 0.026223368
A13: R0 | B13: Greece | C13: DST | D13: 3 | E13: 0.050309319
... A1135: C2 | B1135: Sweden | C1135: Luxury VAT | D1135: 0 | E1135: 0

Sheet Data
A1: country | B1: gni_eur_bn | C1: dst | D1: ad | E1: ftt | F1: wealth | G1: aviation | H1: luxury | I1: custom_cost_pct_gni | J1: population_m
A2: Report rate (%) | C2: 3 | D2: 15 | E2: 0.5 | F2: 0.5 | G2: 20 | H2: 20
A3: Austria | B3: 407.974 | C3: 0.035051253 | D3: 0.080887508 | E3: 0.0064710006 | F3: 0.22550457 | G3: 0.062342355 | H3: 0.3407498 | I3: =SUMPRODUCT(C3:H3,Summary!$C$9:$H$9/$C$2:$H$2) | J3: 9.197213
A4: Belgium | B4: 506.96 | C4: 0.039648098 | D4: 0.036294777 | E4: 0.012052233 | F4: 0.14241755 | G4: 0.05063003 | H4: 0.27144715 | I4: =SUMPRODUCT(C4:H4,Summary!$C$9:$H$9/$C$2:$H$2) | J4: 11.883495
A5: Bulgaria | B5: 52.341 | C5: 0.072600829 | D5: 0.034389866 | E5: 0.00038210963 | F5: 0.076421925 | G5: 0.12036797 | H5: 0.42925056 | I5: =SUMPRODUCT(C5:H5,Summary!$C$9:$H$9/$C$2:$H$2) | J5: 6.43736
A6: Croatia | B6: 58.468 | C6: 0.078675515 | D6: 0.044468769 | E6: 0.00051310118 | F6: 0.061572142 | G6: 0.15165424 | H6: 0.5523858 | I6: =SUMPRODUCT(C6:H6,Summary!$C$9:$H$9/$C$2:$H$2) | J6: 3.87435
A7: Cyprus | B7: 21.99 | C7: 0.072760346 | D7: 0.077307867 | E7: 0.0036380173 | F7: 0.20918599 | G7: 0.30772442 | H7: 0.95785316 | I7: =SUMPRODUCT(C7:H7,Summary!$C$9:$H$9/$C$2:$H$2) | J7: 0.982966
A8: Czechia | B8: 227.573 | C8: 0.07821666 | D8: 0.11556731 | E8: 0.0016697939 | F8: 0.15291796 | G8: 0.045115018 | H8: 0.28383765 | I8: =SUMPRODUCT(C8:H8,Summary!$C$9:$H$9/$C$2:$H$2) | J8: 10.9095
A9: Denmark | B9: 348.366 | C9: 0.031001877 | D9: 0.07406004 | E9: 0.032666793 | F9: 0.15300001 | G9: 0.075688844 | H9: 0.1692959 | I9: =SUMPRODUCT(C9:H9,Summary!$C$9:$H$9/$C$2:$H$2) | J9: 5.992734
A10: Estonia | B10: 30.899 | C10: 0.074436066 | D10: 0.067963365 | E10: 0.00032363507 | F10: 0.09385417 | G10: 0.067965306 | H10: 0.22722624 | I10: =SUMPRODUCT(C10:H10,Summary!$C$9:$H$9/$C$2:$H$2) | J10: 1.369995
A11: Finland | B11: 255.407 | C11: 0.037978599 | D11: 0.052073749 | E11: 0.031831547 | F11: 0.059512856 | G11: 0.065779246 | H11: 0.1594403 | I11: =SUMPRODUCT(C11:H11,Summary!$C$9:$H$9/$C$2:$H$2) | J11: 5.635971
A12: France | B12: 2574.684 | C12: 0.042102254 | D12: 0.065677963 | E12: 0.12040313 | F12: 0.25906092 | G12: 0.048758185 | H12: 0.3381432 | I12: =SUMPRODUCT(C12:H12,Summary!$C$9:$H$9/$C$2:$H$2) | J12: 68.8826
A13: Germany | B13: 3729.498 | C13: 0.026223368 | D13: 0.072395802 | E13: 0.042772513 | F13: 0.22372984 | G13: 0.037789901 | H13: 0.21724928 | I13: =SUMPRODUCT(C13:H13,Summary!$C$9:$H$9/$C$2:$H$2) | J13: 83.57714
A14: Greece | B14: 180.881 | C14: 0.050309319 | D14: 0.029853882 | E14: 0.012549687 | F14: 0.06523626 | G14: 0.32766493 | H14: 0.48908068 | I14: =SUMPRODUCT(C14:H14,Summary!$C$9:$H$9/$C$2:$H$2) | J14: 10.372335
... A29: Sweden | B29: 552.698 | C29: 0.034376821 | D29: 0.10873931 | E29: 0.044346099 | F29: 0.12882261 | G29: 0.048973291 | H29: 0.18038622 | I29: =SUMPRODUCT(C29:H29,Summary!$C$9:$H$9/$C$2:$H$2) | J29: 10.58771

Sheet Cost_pct_GNI_lux
A1: country | B1: R0 | C1: A1 | D1: A2 | E1: B1 | F1: B2 | G1: C1 | H1: C2 | I1: is_frugal
A2: Austria | B2: 0.75100649 | C2: 0.72016794 | D2: 0.70440012 | E2: 0.70468176 | F2: 0.70468176 | G2: 0.58172101 | H2: 0.60303829 | I2: TRUE
A3: Belgium | B3: 0.55248984 | C3: 0.47792318 | D3: 0.76004597 | E3: 0.53322711 | F3: 0.77337 | G3: 0.41902397 | H3: 0.43296775 | I3: FALSE
A4: Bulgaria | B4: 0.73341326 | C4: 0.48679023 | D4: 0.6700612 | E4: 0.63340324 | F4: 0.68304227 | G4: 0.62106949 | H4: 0.66823069 | I4: FALSE
A5: Croatia | B5: 0.88926956 | C5: 0.85231615 | D5: 0.73209937 | E5: 0.96132171 | F5: 0.84037034 | G5: 0.73596713 | H5: 0.79537085 | I5: FALSE
A6: Cyprus | B6: 1.6284698 | C6: 0.85231615 | D6: 0.96018294 | E6: 0.96132171 | F6: 0.96454547 | G6: 1.1015707 | H6: 1.2208209 | I6: FALSE
A7: Czechia | B7: 0.6773244 | C7: 0.85231615 | D7: 0.85162239 | E7: 0.76167298 | F7: 0.84379838 | G7: 0.85188222 | H7: 0.86880209 | I7: FALSE
A8: Denmark | B8: 0.53571346 | C8: 0.62733409 | D8: 0.45505622 | E8: 0.56717588 | F8: 0.44552346 | G8: 0.63446129 | H8: 0.64804605 | I8: FALSE
A9: Estonia | B9: 0.53176878 | C9: 0.58756346 | D9: 0.53900364 | E9: 0.62047929 | F9: 0.54679148 | G9: 0.67894336 | H9: 0.70551928 | I9: FALSE
A10: Finland | B10: 0.4066163 | C10: 0.44918127 | D10: 0.45116789 | E10: 0.40363375 | F10: 0.43639062 | G10: 0.55622504 | H10: 0.5663255 | I10: FALSE
A11: France | B11: 0.87414565 | C11: 0.85231615 | D11: 0.72551293 | E11: 0.92013495 | F11: 0.73845829 | G11: 0.85342436 | H11: 0.81293245 | I11: FALSE
A12: Germany | B12: 0.6201607 | C12: 0.69078057 | D12: 0.70273318 | E12: 0.65359321 | F12: 0.69839363 | G12: 0.57714984 | H12: 0.57081739 | I12: TRUE
A13: Greece | B13: 0.97469475 | C13: 0.62135138 | D13: 0.67357552 | E13: 0.67640443 | F13: 0.70372059 | G13: 0.87926018 | H13: 1.0019379 | I13: FALSE
... A28: Sweden | B28: 0.54564435 | C28: 0.75605272 | D28: 0.59319928 | E28: 0.56790732 | F28: 0.5598554 | G28: 0.77748033 | H28: 0.77476735 | I28: TRUE
A29: European Union (GNI-weighted) | B29: 0.70468176 | C29: 0.70468176 | D29: 0.70468176 | E29: 0.70468176 | F29: 0.70468176 | G29: 0.70468146 | H29: 0.70468146

Sheet State_budget_gain_pct_GNI_lux
A1: country | B1: R0 | C1: A1 | D1: A2 | E1: B1 | F1: B2 | G1: C1 | H1: C2
A2: Austria | B2: 0.37932441 | C2: 0.44303558 | D2: 0.44213338 | E2: 0.36030801 | F2: 0.41911913 | G2: 0.58371443 | H2: 0.58371443
A3: Belgium | B3: 0.39208267 | C3: 0.45579384 | D3: 0.45489165 | E3: 0.37306627 | F3: 0.43187739 | G3: 0.5964727 | H3: 0.5964727
A4: Bulgaria | B4: 0.40413491 | C4: 0.46784608 | D4: 0.46694388 | E4: 0.38511851 | F4: 0.44392963 | G4: 0.60852493 | H4: 0.60852493
A5: Croatia | B5: 0.40413491 | C5: 0.46784608 | D5: 0.46694388 | E5: 0.38511851 | F5: 0.44392963 | G5: 0.60852493 | H5: 0.60852493
A6: Cyprus | B6: 0.40413491 | C6: 0.46784608 | D6: 0.46694388 | E6: 0.38511851 | F6: 0.44392963 | G6: 0.60852493 | H6: 0.60852493
A7: Czechia | B7: 0.40413491 | C7: 0.46784608 | D7: 0.46694388 | E7: 0.38511851 | F7: 0.44392963 | G7: 0.60852493 | H7: 0.60852493
A8: Denmark | B8: 0.40413491 | C8: 0.46784608 | D8: 0.46694388 | E8: 0.38511851 | F8: 0.44392963 | G8: 0.60852493 | H8: 0.60852493
A9: Estonia | B9: 0.40413491 | C9: 0.46784608 | D9: 0.46694388 | E9: 0.38511851 | F9: 0.44392963 | G9: 0.60852493 | H9: 0.60852493
A10: Finland | B10: 0.40413491 | C10: 0.46784608 | D10: 0.46694388 | E10: 0.38511851 | F10: 0.44392963 | G10: 0.60852493 | H10: 0.60852493
A11: France | B11: 0.24162953 | C11: 0.3053407 | D11: 0.3044385 | E11: 0.22261313 | F11: 0.28142425 | G11: 0.44601955 | H11: 0.44601955
A12: Germany | B12: 0.40413491 | C12: 0.46784608 | D12: 0.46694388 | E12: 0.38511851 | F12: 0.44392963 | G12: 0.60852493 | H12: 0.60852493
A13: Greece | B13: 0.39158522 | C13: 0.45529639 | D13: 0.45439419 | E13: 0.37256882 | F13: 0.43137994 | G13: 0.59597524 | H13: 0.59597524
... A29: European Union (GNI-weighted) | B29: 0.35915068 | C29: 0.42286185 | D29: 0.42195966 | E29: 0.34013428 | F29: 0.3989454 | G29: 0.5635407 | H29: 0.5635407

Sheet Cost_by_tax_lux
A1: id | B1: country | C1: tax | D1: rate | E1: cost_pct_gni
A2: R0 | B2: Austria | C2: DST | D2: 3 | E2: 0.035051253
A3: R0 | B3: Belgium | C3: DST | D3: 3 | E3: 0.039648098
A4: R0 | B4: Bulgaria | C4: DST | D4: 3 | E4: 0.072600829
A5: R0 | B5: Croatia | C5: DST | D5: 3 | E5: 0.078675515
A6: R0 | B6: Cyprus | C6: DST | D6: 3 | E6: 0.072760346
A7: R0 | B7: Czechia | C7: DST | D7: 3 | E7: 0.07821666
A8: R0 | B8: Denmark | C8: DST | D8: 3 | E8: 0.031001877
A9: R0 | B9: Estonia | C9: DST | D9: 3 | E9: 0.074436066
A10: R0 | B10: Finland | C10: DST | D10: 3 | E10: 0.037978599
A11: R0 | B11: France | C11: DST | D11: 3 | E11: 0.042102254
A12: R0 | B12: Germany | C12: DST | D12: 3 | E12: 0.026223368
A13: R0 | B13: Greece | C13: DST | D13: 3 | E13: 0.050309319
... A2269: C2 | B2269: Sweden | C2269: Luxury: Yachts | D2269: 0 | E2269: 0

Sheet Data_lux
A1: country | B1: gni_eur_bn | C1: dst | D1: ad | E1: ftt | F1: wealth | G1: aviation | H1: lux_automotive | I1: lux_personal | J1: lux_hospitality | K1: lux_wines | L1: lux_gourmet | M1: lux_design | N1: lux_yachts | O1: custom_cost_pct_gni | P1: population_m
A2: Report rate (%) | C2: 3 | D2: 15 | E2: 0.5 | F2: 0.5 | G2: 20 | H2: 20 | I2: 20 | J2: 20 | K2: 20 | L2: 20 | M2: 20 | N2: 20
A3: Austria | B3: 407.974 | C3: 0.035051253 | D3: 0.080887508 | E3: 0.0064710006 | F3: 0.22550457 | G3: 0.062342355 | H3: 0.10724255 | I3: 0.078026078 | J3: 0.095849052 | K3: 0.026131364 | L3: 0.017672573 | M3: 0.012894631 | N3: 0.0029335521 | O3: =SUMPRODUCT(C3:N3,Summary_lux!$C$9:$N$9/$C$2:$N$2) | P3: 9.197213
A4: Belgium | B4: 506.96 | C4: 0.039648098 | D4: 0.036294777 | E4: 0.012052233 | F4: 0.14241755 | G4: 0.05063003 | H4: 0.13125873 | I4: 0.062150431 | J4: 0.022904111 | K4: 0.020814522 | L4: 0.014076807 | M4: 0.0085591775 | N4: 0.011683371 | O4: =SUMPRODUCT(C4:N4,Summary_lux!$C$9:$N$9/$C$2:$N$2) | P4: 11.883495
A5: Bulgaria | B5: 52.341 | C5: 0.072600829 | D5: 0.034389866 | E5: 0.00038210963 | F5: 0.076421925 | G5: 0.12036797 | H5: 0.055558741 | I5: 0.08286648 | J5: 0.16965852 | K5: 0.046254069 | L5: 0.037537807 | M5: 0.011412132 | N5: 0.025962809 | O5: =SUMPRODUCT(C5:N5,Summary_lux!$C$9:$N$9/$C$2:$N$2) | P5: 6.43736
A6: Croatia | B6: 58.468 | C6: 0.078675515 | D6: 0.044468769 | E6: 0.00051310118 | F6: 0.061572142 | G6: 0.15165424 | H6: 0.038209134 | I6: 0.037992899 | J6: 0.19446401 | K6: 0.021206719 | L6: 0.017210459 | M6: 0.0052322721 | N6: 0.2380703 | O6: =SUMPRODUCT(C6:N6,Summary_lux!$C$9:$N$9/$C$2:$N$2) | P6: 3.87435
A7: Cyprus | B7: 21.99 | C7: 0.072760346 | D7: 0.077307867 | E7: 0.0036380173 | F7: 0.20918599 | G7: 0.30772442 | H7: 0.072985762 | I7: 0.21771815 | J7: 0.46803759 | K7: 0.091143763 | L7: 0.049312231 | M7: 0.0074958785 | N7: 0.051159783 | O7: =SUMPRODUCT(C7:N7,Summary_lux!$C$9:$N$9/$C$2:$N$2) | P7: 0.982966
A8: Czechia | B8: 227.573 | C8: 0.07821666 | D8: 0.11556731 | E8: 0.0016697939 | F8: 0.15291796 | G8: 0.045115018 | H8: 0.11457064 | I8: 0.056490376 | J8: 0.062454685 | K8: 0.023648673 | L8: 0.015353795 | M8: 0.0077796911 | N8: 0.003539788 | O8: =SUMPRODUCT(C8:N8,Summary_lux!$C$9:$N$9/$C$2:$N$2) | P8: 10.9095
A9: Denmark | B9: 348.366 | C9: 0.031001877 | D9: 0.07406004 | E9: 0.032666793 | F9: 0.15300001 | G9: 0.075688844 | H9: 0.042847853 | I9: 0.045523543 | J9: 0.032262796 | K9: 0.014659698 | L9: 0.010310888 | M9: 0.0072338891 | N9: 0.01645723 | O9: =SUMPRODUCT(C9:N9,Summary_lux!$C$9:$N$9/$C$2:$N$2) | P9: 5.992734
A10: Estonia | B10: 30.899 | C10: 0.074436066 | D10: 0.067963365 | E10: 0.00032363507 | F10: 0.09385417 | G10: 0.067965306 | H10: 0.03702828 | I10: 0.044182473 | J10: 0.081412169 | K10: 0.02466159 | L10: 0.020014283 | M10: 0.0060846824 | N10: 0.013842764 | O10: =SUMPRODUCT(C10:N10,Summary_lux!$C$9:$N$9/$C$2:$N$2) | P10: 1.369995
A11: Finland | B11: 255.407 | C11: 0.037978599 | D11: 0.052073749 | E11: 0.031831547 | F11: 0.059512856 | G11: 0.065779246 | H11: 0.040250985 | I11: 0.051458393 | J11: 0.024582712 | K11: 0.015957129 | L11: 0.010360094 | M11: 0.0078741122 | N11: 0.0089568748 | O11: =SUMPRODUCT(C11:N11,Summary_lux!$C$9:$N$9/$C$2:$N$2) | P11: 5.635971
A12: France | B12: 2574.684 | C12: 0.042102254 | D12: 0.065677963 | E12: 0.12040313 | F12: 0.25906092 | G12: 0.048758185 | H12: 0.068046702 | I12: 0.12402332 | J12: 0.055862814 | K12: 0.027690728 | L12: 0.024345317 | M12: 0.0096787415 | N12: 0.028495583 | O12: =SUMPRODUCT(C12:N12,Summary_lux!$C$9:$N$9/$C$2:$N$2) | P12: 68.8826
A13: Germany | B13: 3729.498 | C13: 0.026223368 | D13: 0.072395802 | E13: 0.042772513 | F13: 0.22372984 | G13: 0.037789901 | H13: 0.11984791 | I13: 0.046631605 | J13: 0.01527556 | K13: 0.01388194 | L13: 0.0091536114 | M13: 0.0085626263 | N13: 0.0038960264 | O13: =SUMPRODUCT(C13:N13,Summary_lux!$C$9:$N$9/$C$2:$N$2) | P13: 83.57714
A14: Greece | B14: 180.881 | C14: 0.050309319 | D14: 0.029853882 | E14: 0.012549687 | F14: 0.06523626 | G14: 0.32766493 | H14: 0.033159925 | I14: 0.050726561 | J14: 0.21809791 | K14: 0.021235756 | L14: 0.017234024 | M14: 0.0055887321 | N14: 0.14303777 | O14: =SUMPRODUCT(C14:N14,Summary_lux!$C$9:$N$9/$C$2:$N$2) | P14: 10.372335
... A29: Sweden | B29: 552.698 | C29: 0.034376821 | D29: 0.10873931 | E29: 0.044346099 | F29: 0.12882261 | G29: 0.048973291 | H29: 0.0760961 | I29: 0.043009836 | J29: 0.022014286 | K29: 0.013337251 | L29: 0.0081179535 | M29: 0.0065813225 | N29: 0.011229472 | O29: =SUMPRODUCT(C29:N29,Summary_lux!$C$9:$N$9/$C$2:$N$2) | P29: 10.58771
